templating/__init__.py
templating/templating.py
python_pptx_templating-0.0.4.dist-info/LICENSE
python_pptx_templating-0.0.4.dist-info/METADATA
python_pptx_templating-0.0.4.dist-info/WHEEL
python_pptx_templating-0.0.4.dist-info/top_level.txt
python_pptx_templating-0.0.4.dist-info/RECORD
