Metadata-Version: 2.1
Name: python-pptx-templating
Version: 0.0.4
Summary: A small library that provides PowerPoint content templating on top of python-pptx
Home-page: https://pypi.org/project/python-pptx-templating/
Author: Serhiy Masyutin
Author-email: serg.masyutin@gmail.com
Project-URL: GitLab, https://gitlab.com/serg.masyutin/python-pptx-templating
Classifier: Programming Language :: Python :: 3
Classifier: License :: OSI Approved :: MIT License
Classifier: Operating System :: OS Independent
Requires-Python: >=3.6
License-File: LICENSE
Requires-Dist: chevron (>=0.14.0)
Requires-Dist: python-pptx (>=0.6.21)
